mead.py
stormheron_mead_calc-0.2.dist-info/LICENSE
stormheron_mead_calc-0.2.dist-info/METADATA
stormheron_mead_calc-0.2.dist-info/WHEEL
stormheron_mead_calc-0.2.dist-info/top_level.txt
stormheron_mead_calc-0.2.dist-info/RECORD
