Metadata-Version: 2.1
Name: stormheron-mead-calc
Version: 0.2
Summary: an abstraction layer for the stormheron mead-calc API
Home-page: https://gitlab.com/stormheron/mead-calc
Author: Stormheron
License: UNKNOWN
Platform: UNKNOWN
Classifier: Programming Language :: Python :: 3
Classifier: License :: OSI Approved :: GNU General Public License (GPL)
Classifier: Operating System :: OS Independent
Requires-Python: >=3.6
